{
    "CASE_ID": "042026064513468",
    "CASE_DT": "2026\/6\/25 上午 09:28:00",
    "COUNTY_N": "屏東縣",
    "TOWN_N": "屏東市",
    "CASE_LOC": "屏東縣屏東市工業區羅德食品公司",
    "GEOMETRY_TYPE": "點",
    "COORDINATE": "120.4799948,22.6647375",
    "DISASTER_MAIN_TYPE": "積淹水災情",
    "DISASTER_SUB_TYPE": "道路積淹水",
    "CASE_DESCRIPTION": "屏東工業區工業路羅德食品公司附近道路積淹水,目前人車受困約2-30人",
    "CASE_STATUS": "處理中",
    "CASE_TYPE": "災情查報",
    "PERSON_ID": "何小姐",
    "INJURED_NO": 0,
    "DEATH_NO": 0,
    "TRAPPED_NO": 0,
    "MISSING_NO": 0,
    "SHELTER_NO": 0,
    "IS_TRAFFIC": false,
    "IS_SERIOUS": false,
    "logs": [
        {
            "field": "CASE_STATUS",
            "old_value": "待處理",
            "new_value": "處理中",
            "timestamp": "2026-06-25 09:51:09"
        }
    ]
}