{
    "CASE_ID": "042025062014691",
    "CASE_DT": "2025\/7\/21 上午 09:06:00",
    "COUNTY_N": "臺東縣",
    "TOWN_N": "海端鄉",
    "CASE_LOC": "臺東縣海端鄉台20 186.5K處 下馬路段",
    "GEOMETRY_TYPE": "點",
    "COORDINATE": "121.0175672,23.11478528",
    "DISASTER_MAIN_TYPE": "土石災情",
    "DISASTER_SUB_TYPE": "土石崩落",
    "CASE_DESCRIPTION": "台20 186.5K處 下馬路段土石崩落交通中斷",
    "CASE_STATUS": "待處理",
    "CASE_TYPE": "災情查報",
    "PERSON_ID": "119",
    "INJURED_NO": 0,
    "DEATH_NO": 0,
    "TRAPPED_NO": 0,
    "MISSING_NO": 0,
    "SHELTER_NO": 0,
    "IS_TRAFFIC": true,
    "IS_SERIOUS": false,
    "logs": []
}