{
    "CASE_ID": "042025062111305",
    "CASE_DT": "2025\/8\/3 上午 09:27:00",
    "COUNTY_N": "嘉義縣",
    "TOWN_N": "布袋鎮",
    "CASE_LOC": "嘉義縣布袋鎮新岑里",
    "GEOMETRY_TYPE": "點",
    "COORDINATE": "120.174224,23.342153",
    "DISASTER_MAIN_TYPE": "積淹水災情",
    "DISASTER_SUB_TYPE": "其他",
    "CASE_DESCRIPTION": "新岑公園水溝溢滿流出路面！北邊?田水位還沒下降",
    "CASE_STATUS": "處理中",
    "CASE_TYPE": "災情查報",
    "PERSON_ID": "蔡政擧里長",
    "INJURED_NO": 0,
    "DEATH_NO": 0,
    "TRAPPED_NO": 0,
    "MISSING_NO": 0,
    "SHELTER_NO": 0,
    "IS_TRAFFIC": false,
    "IS_SERIOUS": false,
    "logs": [
        {
            "field": "CASE_STATUS",
            "old_value": "待處理",
            "new_value": "處理中",
            "timestamp": "2025-08-03 10:01:04"
        }
    ]
}