{
    "CASE_ID": "042025061880986",
    "CASE_DT": "2025\/7\/10 上午 06:30:00",
    "COUNTY_N": "屏東縣",
    "TOWN_N": "獅子鄉",
    "CASE_LOC": "屏東縣獅子鄉[屏東縣獅子鄉丹路村7鄰巴士巷70號]",
    "GEOMETRY_TYPE": "點",
    "COORDINATE": "120.76338273265398,22.213011789403282",
    "DISASTER_MAIN_TYPE": "土石災情",
    "DISASTER_SUB_TYPE": "土石崩落",
    "CASE_DESCRIPTION": "丹路村巴士墨段產業道路邊坡崩塌土石淹埋道路，電線杆倒塌停電。已完成清除土石，恢復道路通行",
    "CASE_STATUS": "處理中",
    "CASE_TYPE": "災情查報",
    "PERSON_ID": "東家榮",
    "INJURED_NO": 0,
    "DEATH_NO": 0,
    "TRAPPED_NO": 0,
    "MISSING_NO": 0,
    "SHELTER_NO": 0,
    "IS_TRAFFIC": true,
    "IS_SERIOUS": false,
    "logs": [
        {
            "field": "CASE_STATUS",
            "old_value": "待處理",
            "new_value": "處理中",
            "timestamp": "2025-07-10 08:01:05"
        },
        {
            "field": "CASE_DESCRIPTION",
            "old_value": "丹路村巴士末段產業道路邊坡崩塌土石淹埋道路，電線杆倒塌停電。",
            "new_value": "丹路村巴士墨段產業道路邊坡崩塌土石淹埋道路，電線杆倒塌停電。",
            "timestamp": "2025-07-10 09:01:04"
        },
        {
            "field": "CASE_DESCRIPTION",
            "old_value": "丹路村巴士墨段產業道路邊坡崩塌土石淹埋道路，電線杆倒塌停電。",
            "new_value": "丹路村巴士墨段產業道路邊坡崩塌土石淹埋道路，電線杆倒塌停電。已完成清除土石，恢復道路通行",
            "timestamp": "2025-07-11 11:31:04"
        }
    ]
}