{
    "CASE_ID": "042026064601007",
    "CASE_DT": "2026\/7\/11 下午 01:11:00",
    "COUNTY_N": "高雄市",
    "TOWN_N": "左營區",
    "CASE_LOC": "高雄市左營區文川路和崇和路口(明倫幼稚園)",
    "GEOMETRY_TYPE": "點",
    "COORDINATE": "120.307301,22.679803",
    "DISASTER_MAIN_TYPE": "廣告招牌災情",
    "DISASTER_SUB_TYPE": "廣告招牌欲墜",
    "CASE_DESCRIPTION": "布幕快飛走",
    "CASE_STATUS": "已處理",
    "CASE_TYPE": "災情查報",
    "PERSON_ID": "郭先生",
    "INJURED_NO": 0,
    "DEATH_NO": 0,
    "TRAPPED_NO": 0,
    "MISSING_NO": 0,
    "SHELTER_NO": 0,
    "IS_TRAFFIC": false,
    "IS_SERIOUS": false,
    "logs": [
        {
            "field": "CASE_STATUS",
            "old_value": "待處理",
            "new_value": "處理中",
            "timestamp": "2026-07-11 13:31:04"
        },
        {
            "field": "CASE_STATUS",
            "old_value": "處理中",
            "new_value": "已處理",
            "timestamp": "2026-07-11 21:31:04"
        }
    ]
}