{
    "CASE_ID": "042025060867710",
    "CASE_DT": "2025\/7\/7 下午 12:53:00",
    "COUNTY_N": "屏東縣",
    "TOWN_N": "獅子鄉",
    "CASE_LOC": "屏東縣獅子鄉[屏東縣獅子鄉丹路村4鄰丹路二巷11號之1]",
    "GEOMETRY_TYPE": "點",
    "COORDINATE": "120.7747398743705,22.213354631006922",
    "DISASTER_MAIN_TYPE": "道路、隧道災情",
    "DISASTER_SUB_TYPE": "路基流失",
    "CASE_DESCRIPTION": "牡丹路農路路基掏空",
    "CASE_STATUS": "待處理",
    "CASE_TYPE": "災情查報",
    "PERSON_ID": "高基銘",
    "INJURED_NO": 0,
    "DEATH_NO": 0,
    "TRAPPED_NO": 0,
    "MISSING_NO": 0,
    "SHELTER_NO": 0,
    "IS_TRAFFIC": false,
    "IS_SERIOUS": false,
    "logs": []
}