{
    "CASE_ID": "072025062190782",
    "CASE_DT": "2025\/8\/13 下午 05:20:42",
    "COUNTY_N": "臺南市",
    "TOWN_N": "北門區",
    "CASE_LOC": "台南市北門區永隆里北門141號",
    "GEOMETRY_TYPE": "點",
    "COORDINATE": "120.121888273838,23.269959725583",
    "DISASTER_MAIN_TYPE": "民生、基礎設施災情",
    "DISASTER_SUB_TYPE": "電線（桿）毀損",
    "CASE_DESCRIPTION": "2025\/08\/13 17:20:42 - 剛電線走火目前有煙人已外出2025\/08\/13 17:27:51 - 平房.剛電線走火目前有煙人已外出2025\/08\/13 17:34:24 - 北門01回報:戶外電桶爆炸.已無狀況.不需支援",
    "CASE_STATUS": "處理中",
    "CASE_TYPE": "119消防署派遣系統",
    "PERSON_ID": "",
    "INJURED_NO": 0,
    "DEATH_NO": 0,
    "TRAPPED_NO": 0,
    "MISSING_NO": 0,
    "SHELTER_NO": 0,
    "IS_TRAFFIC": false,
    "IS_SERIOUS": false,
    "logs": [
        {
            "field": "CASE_STATUS",
            "old_value": "待處理",
            "new_value": "處理中",
            "timestamp": "2025-08-13 19:11:04"
        }
    ]
}