{
    "CASE_ID": "072025060726899",
    "CASE_DT": "2025\/7\/6 下午 08:32:55",
    "COUNTY_N": "臺南市",
    "TOWN_N": "東區",
    "CASE_LOC": "台南市東區林森路一段149號(颱風)",
    "GEOMETRY_TYPE": "點",
    "COORDINATE": "120.214805303915,22.982425035569",
    "DISASTER_MAIN_TYPE": "車輛、交通事故",
    "DISASTER_SUB_TYPE": "車禍",
    "CASE_DESCRIPTION": "2025\/07\/06 20:32:55 - 地點描述：台南市東區林森路一段149號管理室騎機車撞到掉落的椰子樹（林森路\/大同路）110轉報人員：葉修汶",
    "CASE_STATUS": "已處理",
    "CASE_TYPE": "119消防署派遣系統",
    "PERSON_ID": "",
    "INJURED_NO": 0,
    "DEATH_NO": 0,
    "TRAPPED_NO": 0,
    "MISSING_NO": 0,
    "SHELTER_NO": 0,
    "IS_TRAFFIC": false,
    "IS_SERIOUS": false,
    "logs": [
        {
            "field": "CASE_STATUS",
            "old_value": "待處理",
            "new_value": "已處理",
            "timestamp": "2025-07-06 21:05:04"
        }
    ]
}