{
    "CASE_ID": "072025062479421",
    "CASE_DT": "2025\/9\/23 下午 11:05:21",
    "COUNTY_N": "花蓮縣",
    "TOWN_N": "光復鄉",
    "CASE_LOC": "花蓮縣光復鄉仁愛路16巷9號(受困)",
    "GEOMETRY_TYPE": "點",
    "COORDINATE": "121.425732897462,23.6671534829431",
    "DISASTER_MAIN_TYPE": "其他災情",
    "DISASTER_SUB_TYPE": "其他",
    "CASE_DESCRIPTION": "2025\/09\/23 23:05:21 - 人員受困建物3樓",
    "CASE_STATUS": "未指派",
    "CASE_TYPE": "119消防署派遣系統",
    "PERSON_ID": "",
    "INJURED_NO": 0,
    "DEATH_NO": 0,
    "TRAPPED_NO": 0,
    "MISSING_NO": 0,
    "SHELTER_NO": 0,
    "IS_TRAFFIC": false,
    "IS_SERIOUS": false,
    "logs": []
}