{
    "CASE_ID": "102025062714841",
    "CASE_DT": "2025\/10\/21 下午 07:55:19",
    "COUNTY_N": "桃園市",
    "TOWN_N": "觀音區",
    "CASE_LOC": "環中路275巷16衖12號旁",
    "GEOMETRY_TYPE": "點",
    "COORDINATE": "121.136285480265,25.0117095265969",
    "DISASTER_MAIN_TYPE": "積淹水災情",
    "DISASTER_SUB_TYPE": "道路積淹水",
    "CASE_DESCRIPTION": "11410210432、道路積淹水、民眾反映地點：觀音區環中路275巷16衖12號旁事由：上址住家是一位老人的住家，於10\/20道路淹水至民眾住家內，目前已淹至膝蓋高度，老人家養雞的位置也淹水，老人家這兩天不段舀水，民眾昨天已協助通報，但至今水仍未退散，先前道路尚未鋪柏油時不會淹水，鋪完之後就淹水了，要求盡快派員排水。本案不清楚可與民眾聯繫，民眾電話僅供承辦單位業務聯繫",
    "CASE_STATUS": "未指派",
    "CASE_TYPE": "1999報災情",
    "PERSON_ID": "王柏軒",
    "INJURED_NO": 0,
    "DEATH_NO": 0,
    "TRAPPED_NO": 0,
    "MISSING_NO": 0,
    "SHELTER_NO": 0,
    "IS_TRAFFIC": false,
    "IS_SERIOUS": false,
    "logs": []
}