{
    "CASE_ID": "102025061924546",
    "CASE_DT": "2025\/7\/9 上午 09:58:00",
    "COUNTY_N": "臺南市",
    "TOWN_N": "佳里區",
    "CASE_LOC": "臺南市佳里區",
    "GEOMETRY_TYPE": "點",
    "COORDINATE": ",",
    "DISASTER_MAIN_TYPE": "民生、基礎設施災情",
    "DISASTER_SUB_TYPE": "電力停電",
    "CASE_DESCRIPTION": "民眾陳情資訊如下：受文者???? ： 臺南市政府移文處理註記?： 本件已併移行政院信件編號：2025016626.1標?????? 題：總統救救我們子龍里整個家園內?????? 容：親愛的總統：我很尊敬您因為您當市長時，我陳情過您的信箱，三日內您就幫忙我們平民老百姓，這次颱風我們位於台南市佳里區麻佳路三段288號（子龍廟）這區里民，我求助過台南應變中心-覆電單位，他們回覆的時間一改再改， 我們這區務農人居多，不會網路，里長沒有作為，連續兩天有老人孩子的都睡車上，我家鐵門老舊，只能開啟30公分，大人小孩都爬的出門找飯找水，路邊電線桿大樹倒塌，單位先處理的區域都是鎮內鬧區，我們住在外圍的鄉下很無助也無能 ，希望可以幫幫我們，目前還在廟宇空地才有訊號，可以幫我們盡快覆電嗎？ 我們做小生意的損失慘重，務農要重建家園，沒電動不了，我們好像被政府拋棄了?? 台南市佳里區麻佳路三段288號 （子龍里民）敬上發信日期：2025-07-08驗證日期：2025-07-08",
    "CASE_STATUS": "處理中",
    "CASE_TYPE": "1999報災情",
    "PERSON_ID": "賴依青",
    "INJURED_NO": 0,
    "DEATH_NO": 0,
    "TRAPPED_NO": 0,
    "MISSING_NO": 0,
    "SHELTER_NO": 0,
    "IS_TRAFFIC": false,
    "IS_SERIOUS": false,
    "logs": [
        {
            "field": "CASE_STATUS",
            "old_value": "未指派",
            "new_value": "待處理",
            "timestamp": "2025-07-10 13:31:04"
        },
        {
            "field": "CASE_STATUS",
            "old_value": "待處理",
            "new_value": "處理中",
            "timestamp": "2025-07-12 00:31:05"
        }
    ]
}