{
    "CASE_ID": "102025061915031",
    "CASE_DT": "2025\/7\/10 上午 09:34:00",
    "COUNTY_N": "臺南市",
    "TOWN_N": "下營區",
    "CASE_LOC": "下營區紅甲里17鄰中庄子66號",
    "GEOMETRY_TYPE": "點",
    "COORDINATE": ",",
    "DISASTER_MAIN_TYPE": "民生、基礎設施災情",
    "DISASTER_SUB_TYPE": "電力停電",
    "CASE_DESCRIPTION": "EMIC派工下營區紅甲里17鄰中庄子66號(此為民眾的住家地址,目前也停電),位於64與65號中間的位置,有台電電線,因颱風天關係,有垂落斷裂的情況,民眾擔憂其危險性,請速派員處理,煩卓處，若不清楚可致電民眾洽詢。",
    "CASE_STATUS": "未指派",
    "CASE_TYPE": "1999報災情",
    "PERSON_ID": "顏先生",
    "INJURED_NO": 0,
    "DEATH_NO": 0,
    "TRAPPED_NO": 0,
    "MISSING_NO": 0,
    "SHELTER_NO": 0,
    "IS_TRAFFIC": false,
    "IS_SERIOUS": false,
    "logs": []
}