{
    "CASE_ID": "102025062284118",
    "CASE_DT": "2025\/7\/6 下午 07:48:48",
    "COUNTY_N": "桃園市",
    "TOWN_N": "桃園區",
    "CASE_LOC": "民權路69巷2號",
    "GEOMETRY_TYPE": "點",
    "COORDINATE": "121.310245902116,24.993167055472",
    "DISASTER_MAIN_TYPE": "其他災情",
    "DISASTER_SUB_TYPE": "其他",
    "CASE_DESCRIPTION": "11407060249、棚子倒塌、景福派出所通報地點:桃園區民權路69巷2號(長青活動中心)事由:文昌公園內長青活動中心前有搭棚子，目前棚子沒有加固，風大被風吹倒，差點壓到在公園活動路過的民眾，請派員前往處理本案不清楚可與民眾聯繫，民眾電話僅供承辦單位業務聯繫",
    "CASE_STATUS": "未指派",
    "CASE_TYPE": "1999報災情",
    "PERSON_ID": "值班員警",
    "INJURED_NO": 0,
    "DEATH_NO": 0,
    "TRAPPED_NO": 0,
    "MISSING_NO": 0,
    "SHELTER_NO": 0,
    "IS_TRAFFIC": false,
    "IS_SERIOUS": false,
    "logs": []
}