{
    "CASE_ID": "112026064515911",
    "CASE_DT": "2026\/6\/25 下午 04:21:00",
    "COUNTY_N": "臺北市",
    "TOWN_N": "北投區",
    "CASE_LOC": "臺北市北投區奇岩里崇仰一路3號",
    "GEOMETRY_TYPE": "點",
    "COORDINATE": ",",
    "DISASTER_MAIN_TYPE": "土石災情",
    "DISASTER_SUB_TYPE": "土石崩落",
    "CASE_DESCRIPTION": "該地址前有落石",
    "CASE_STATUS": "處理中",
    "CASE_TYPE": "縣市報災情",
    "PERSON_ID": "奇岩里里長",
    "INJURED_NO": 0,
    "DEATH_NO": 0,
    "TRAPPED_NO": 0,
    "MISSING_NO": 0,
    "SHELTER_NO": 0,
    "IS_TRAFFIC": false,
    "IS_SERIOUS": false,
    "logs": []
}