{
    "CASE_ID": "112026064519932",
    "CASE_DT": "2026\/6\/26 上午 08:27:14",
    "COUNTY_N": "新竹市",
    "TOWN_N": "北區",
    "CASE_LOC": "新竹市福林里境福街86號至128號之間",
    "GEOMETRY_TYPE": "點",
    "COORDINATE": "120.960427,24.818856",
    "DISASTER_MAIN_TYPE": "積淹水災情",
    "DISASTER_SUB_TYPE": "道路積淹水",
    "CASE_DESCRIPTION": "時雨量過大，排水不及，造成道路積淹水嚴重，交通大打結。",
    "CASE_STATUS": "處理中",
    "CASE_TYPE": "縣市報災情",
    "PERSON_ID": "呂尚濬",
    "INJURED_NO": 0,
    "DEATH_NO": 0,
    "TRAPPED_NO": 0,
    "MISSING_NO": 0,
    "SHELTER_NO": 0,
    "IS_TRAFFIC": false,
    "IS_SERIOUS": false,
    "logs": []
}