{
    "CASE_ID": "112026064604755",
    "CASE_DT": "2026\/7\/12 上午 09:40:00",
    "COUNTY_N": "臺北市",
    "TOWN_N": "士林區",
    "CASE_LOC": "中社路一段60巷及中社路二段17巷、20巷",
    "GEOMETRY_TYPE": "點",
    "COORDINATE": "121.56049,25.107637",
    "DISASTER_MAIN_TYPE": "路樹災情",
    "DISASTER_SUB_TYPE": "路樹倒塌",
    "CASE_DESCRIPTION": "【一般案件】民眾反映中社路一段和中社路一段60巷交叉路口處，位於中社路一段上，因颱風因素造成竹林倒塌，要求相關單位介入處理。民眾反映中社路二段和中社路二段17巷交叉路口附近，位於中社路二段往下山的方向處的小公園處，因颱風因素造成樹路倒塌，要求相關單位介入處理",
    "CASE_STATUS": "已處理",
    "CASE_TYPE": "縣市報災情",
    "PERSON_ID": "阮語婕",
    "INJURED_NO": 0,
    "DEATH_NO": 0,
    "TRAPPED_NO": 0,
    "MISSING_NO": 0,
    "SHELTER_NO": 0,
    "IS_TRAFFIC": false,
    "IS_SERIOUS": false,
    "logs": []
}