{
    "CASE_ID": "172025062721550",
    "CASE_DT": "2025\/10\/28 上午 11:55:13",
    "COUNTY_N": "基隆市",
    "TOWN_N": "中正區",
    "CASE_LOC": "基隆市中正區德義里12鄰信二路299號",
    "GEOMETRY_TYPE": "點",
    "COORDINATE": "121.7460443,25.1307373",
    "DISASTER_MAIN_TYPE": "其他災情",
    "DISASTER_SUB_TYPE": "其他",
    "CASE_DESCRIPTION": "北寧路考碧砂魚港一側山坡滑落，目前只能一個線道通行",
    "CASE_STATUS": "未受理",
    "CASE_TYPE": "民眾版LINE災情通報",
    "PERSON_ID": "楊鈞耀",
    "INJURED_NO": 0,
    "DEATH_NO": 0,
    "TRAPPED_NO": 0,
    "MISSING_NO": 0,
    "SHELTER_NO": 0,
    "IS_TRAFFIC": false,
    "IS_SERIOUS": false,
    "logs": []
}