{
    "CASE_ID": "182025062439548",
    "CASE_DT": "2025\/9\/17 上午 10:16:00",
    "COUNTY_N": "宜蘭縣",
    "TOWN_N": "五結鄉",
    "CASE_LOC": "宜蘭縣五結鄉崙仔村崙頂路80號",
    "GEOMETRY_TYPE": "點",
    "COORDINATE": "121.8058342,24.68887343",
    "DISASTER_MAIN_TYPE": "車輛、交通事故",
    "DISASTER_SUB_TYPE": "車禍",
    "CASE_DESCRIPTION": "[現場狀況]自用小客車為閃避羊群而擦撞安全島，小客車翻覆，造成2名受傷1名受困。",
    "CASE_STATUS": "未指派",
    "CASE_TYPE": "災情匯入",
    "PERSON_ID": "陳曉貞",
    "INJURED_NO": 0,
    "DEATH_NO": 0,
    "TRAPPED_NO": 0,
    "MISSING_NO": 0,
    "SHELTER_NO": 0,
    "IS_TRAFFIC": false,
    "IS_SERIOUS": false,
    "logs": []
}