{
    "type": "FeatureCollection",
    "features": [
        {
            "type": "Feature",
            "geometry": {
                "type": "Point",
                "coordinates": [
                    120.5867362,
                    24.3463192
                ]
            },
            "properties": {
                "CASE_ID": "162026064244943",
                "CASE_DT": "2026\/5\/15 下午 03:47:56",
                "DISASTER_MAIN_TYPE": "廣告招牌災情",
                "CASE_STATUS": "未指派",
                "IS_TRAFFIC": true,
                "IS_SERIOUS": false
            }
        },
        {
            "type": "Feature",
            "geometry": {
                "type": "Point",
                "coordinates": [
                    120.5867058,
                    24.3462635
                ]
            },
            "properties": {
                "CASE_ID": "162026064244904",
                "CASE_DT": "2026\/5\/15 下午 03:44:35",
                "DISASTER_MAIN_TYPE": "路樹災情",
                "CASE_STATUS": "未指派",
                "IS_TRAFFIC": false,
                "IS_SERIOUS": false
            }
        },
        {
            "type": "Feature",
            "geometry": {
                "type": "Point",
                "coordinates": [
                    120.5866894,
                    24.3462656
                ]
            },
            "properties": {
                "CASE_ID": "162026064244897",
                "CASE_DT": "2026\/5\/15 下午 03:44:09",
                "DISASTER_MAIN_TYPE": "路樹災情",
                "CASE_STATUS": "未指派",
                "IS_TRAFFIC": false,
                "IS_SERIOUS": false
            }
        },
        {
            "type": "Feature",
            "geometry": {
                "type": "Point",
                "coordinates": [
                    120.5914407,
                    24.3650956
                ]
            },
            "properties": {
                "CASE_ID": "162026064244896",
                "CASE_DT": "2026\/5\/15 下午 03:42:48",
                "DISASTER_MAIN_TYPE": "路樹災情",
                "CASE_STATUS": "未指派",
                "IS_TRAFFIC": false,
                "IS_SERIOUS": false
            }
        },
        {
            "type": "Feature",
            "geometry": {
                "type": "Point",
                "coordinates": [
                    120.5866452,
                    24.346218
                ]
            },
            "properties": {
                "CASE_ID": "162026064244882",
                "CASE_DT": "2026\/5\/15 下午 03:42:34",
                "DISASTER_MAIN_TYPE": "路樹災情",
                "CASE_STATUS": "未指派",
                "IS_TRAFFIC": true,
                "IS_SERIOUS": false
            }
        },
        {
            "type": "Feature",
            "geometry": {
                "type": "Point",
                "coordinates": [
                    120.5867543,
                    24.3462973
                ]
            },
            "properties": {
                "CASE_ID": "162026064244899",
                "CASE_DT": "2026\/5\/15 下午 03:41:49",
                "DISASTER_MAIN_TYPE": "路樹災情",
                "CASE_STATUS": "未指派",
                "IS_TRAFFIC": true,
                "IS_SERIOUS": false
            }
        },
        {
            "type": "Feature",
            "geometry": {
                "type": "Point",
                "coordinates": [
                    120.5914407,
                    24.3650956
                ]
            },
            "properties": {
                "CASE_ID": "162026064244894",
                "CASE_DT": "2026\/5\/15 下午 03:41:49",
                "DISASTER_MAIN_TYPE": "其他災情",
                "CASE_STATUS": "未指派",
                "IS_TRAFFIC": true,
                "IS_SERIOUS": false
            }
        },
        {
            "type": "Feature",
            "geometry": {
                "type": "Point",
                "coordinates": [
                    120.5866077,
                    24.346195
                ]
            },
            "properties": {
                "CASE_ID": "162026064244890",
                "CASE_DT": "2026\/5\/15 下午 03:41:38",
                "DISASTER_MAIN_TYPE": "路樹災情",
                "CASE_STATUS": "未指派",
                "IS_TRAFFIC": false,
                "IS_SERIOUS": false
            }
        },
        {
            "type": "Feature",
            "geometry": {
                "type": "Point",
                "coordinates": [
                    120.5866813,
                    24.3463532
                ]
            },
            "properties": {
                "CASE_ID": "162026064244891",
                "CASE_DT": "2026\/5\/15 下午 03:41:37",
                "DISASTER_MAIN_TYPE": "道路、隧道災情",
                "CASE_STATUS": "未指派",
                "IS_TRAFFIC": false,
                "IS_SERIOUS": false
            }
        },
        {
            "type": "Feature",
            "geometry": {
                "type": "Point",
                "coordinates": [
                    120.5866967,
                    24.346368
                ]
            },
            "properties": {
                "CASE_ID": "162026064244952",
                "CASE_DT": "2026\/5\/15 下午 03:41:03",
                "DISASTER_MAIN_TYPE": "路樹災情",
                "CASE_STATUS": "未指派",
                "IS_TRAFFIC": false,
                "IS_SERIOUS": false
            }
        }
    ]
}